<?xml version="1.0" encoding="utf-8" standalone="no"?>
<dublin_core schema="dcterms">
  <dcvalue element="abstract" qualifier="none" language="">The&#x20;Stollery&#x20;Children&#x20;s&#x20;Hospital&#x20;serves&#x20;a&#x20;very&#x20;large&#x20;geographic&#x20;region&#x20;of&#x20;over&#x20;at&#x20;least&#x20;650&#x20;000&#x20;km&#x20;with&#x20;patients&#x20;from&#x20;outside&#x20;of&#x20;Edmonton&#x20;accounting&#x20;for&#x20;approximately&#x20;50&#x20;of&#x20;the&#x20;service&#x20;population&#x20;The&#x20;aim&#x20;of&#x20;this&#x20;study&#x20;is&#x20;to&#x20;document&#x20;the&#x20;experience&#x20;and&#x20;opinion&#x20;of&#x20;the&#x20;patient&#x20;and&#x20;clinician&#x20;satisfaction&#x20;with&#x20;telehealth&#x20;encounter&#x20;for&#x20;various&#x20;pediatric&#x20;surgical&#x20;consultations&#x20;and&#x20;follow&#x20;up&#x20;as&#x20;a&#x20;way&#x20;to&#x20;bridge&#x20;the&#x20;distance&#x20;gap</dcvalue>
  <dcvalue element="contributor" qualifier="none" language="">Shivji,&#x20;Salma</dcvalue>
  <dcvalue element="contributor" qualifier="none" language="">Metcalfe,&#x20;Peter</dcvalue>
  <dcvalue element="contributor" qualifier="none" language="">Khan,&#x20;Allvena</dcvalue>
  <dcvalue element="contributor" qualifier="none" language="">Bratu,&#x20;Ioana</dcvalue>
  <dcvalue element="identifier" qualifier="none" language="">http:&#x2F;&#x2F;dx.doi.org&#x2F;10.1007&#x2F;s00383-010-2823-y</dcvalue>
  <dcvalue element="relation" qualifier="none" language="">Pediatric&#x20;surgery&#x20;international</dcvalue>
  <dcvalue element="title" qualifier="none" language="en">Pediatric&#x20;surgery&#x20;telehealth:&#x20;patient&#x20;and&#x20;clinician&#x20;satisfaction.</dcvalue>
</dublin_core>
