<?xml version="1.0" encoding="utf-8" standalone="no"?>
<dublin_core schema="dcterms">
  <dcvalue element="contributor" qualifier="none" language="">Yngve,&#x20;Agneta</dcvalue>
  <dcvalue element="contributor" qualifier="none" language="">Tseng,&#x20;Marilyn</dcvalue>
  <dcvalue element="contributor" qualifier="none" language="">Hodge,&#x20;Allison</dcvalue>
  <dcvalue element="contributor" qualifier="none" language="">McNeill,&#x20;Geraldine</dcvalue>
  <dcvalue element="contributor" qualifier="none" language="">Haapala,&#x20;Irja</dcvalue>
  <dcvalue element="identifier" qualifier="none" language="">http:&#x2F;&#x2F;dx.doi.org&#x2F;10.1017&#x2F;S1368980011000218</dcvalue>
  <dcvalue element="relation" qualifier="none" language="">Public&#x20;health&#x20;nutrition</dcvalue>
  <dcvalue element="title" qualifier="none" language="en">Assessment&#x20;of&#x20;diet&#x20;and&#x20;physical&#x20;activity:&#x20;new&#x20;tools;&#x20;old&#x20;challenges.</dcvalue>
</dublin_core>
