<?xml version="1.0" encoding="utf-8" standalone="no"?>
<dublin_core schema="dcterms">
  <dcvalue element="abstract" qualifier="none" language="">This&#x20;study&#x20;determined&#x20;the&#x20;effectiveness&#x20;of&#x20;a&#x20;commercially&#x20;produced&#x20;handheld&#x20;computer&#x20;as&#x20;a&#x20;prompting&#x20;system&#x20;in&#x20;facilitating&#x20;the&#x20;generalization&#x20;and&#x20;increasing&#x20;the&#x20;probability&#x20;of&#x20;long&#x20;term&#x20;maintenance&#x20;of&#x20;vocational&#x20;skills&#x20;by&#x20;adolescents&#x20;with&#x20;moderate&#x20;intellectual&#x20;disabilities&#x20;Four&#x20;students&#x20;successfully&#x20;used&#x20;the&#x20;system&#x20;in&#x20;learning&#x20;a&#x20;task&#x20;and&#x20;then&#x20;generalized&#x20;the&#x20;use&#x20;of&#x20;the&#x20;prompting&#x20;system&#x20;to&#x20;complete&#x20;increasingly&#x20;more&#x20;complex&#x20;tasks&#x20;Task&#x20;performance&#x20;was&#x20;maintained&#x20;at&#x20;a&#x20;100&#x20;level&#x20;for&#x20;up&#x20;to&#x20;9&#x20;weeks</dcvalue>
  <dcvalue element="contributor" qualifier="none" language="">Cihak,&#x20;David&#x20;F</dcvalue>
  <dcvalue element="contributor" qualifier="none" language="">Kessler,&#x20;Kelby&#x20;B</dcvalue>
  <dcvalue element="contributor" qualifier="none" language="">Alberto,&#x20;Paul&#x20;A</dcvalue>
  <dcvalue element="identifier" qualifier="none" language="">http:&#x2F;&#x2F;dx.doi.org&#x2F;10.1016&#x2F;j.ridd.2006.05.003</dcvalue>
  <dcvalue element="relation" qualifier="none" language="">Research&#x20;in&#x20;developmental&#x20;disabilities</dcvalue>
  <dcvalue element="title" qualifier="none" language="en">Generalized&#x20;use&#x20;of&#x20;a&#x20;handheld&#x20;prompting&#x20;system.</dcvalue>
</dublin_core>
