<?xml version="1.0" encoding="utf-8" standalone="no"?>
<dublin_core schema="dc">
  <dcvalue element="contributor" qualifier="author" language="">Helveston,&#x20;E&#x20;M</dcvalue>
  <dcvalue element="contributor" qualifier="author" language="">Orge,&#x20;F&#x20;H</dcvalue>
  <dcvalue element="contributor" qualifier="author" language="">Naranjo,&#x20;R</dcvalue>
  <dcvalue element="contributor" qualifier="author" language="">Hernandez,&#x20;L</dcvalue>
  <dcvalue element="date" qualifier="accessioned">2020-02-12T12:01:33Z</dcvalue>
  <dcvalue element="date" qualifier="available">2020-02-12T12:01:33Z</dcvalue>
  <dcvalue element="date" qualifier="issued" language="">2001-10-19</dcvalue>
  <dcvalue element="identifier" qualifier="uri" language="">http:&#x2F;&#x2F;dx.doi.org&#x2F;Not&#x20;available</dcvalue>
  <dcvalue element="identifier" qualifier="uri">https:&#x2F;&#x2F;lib.digitalsquare.io&#x2F;xmlui&#x2F;handle&#x2F;123456789&#x2F;59283</dcvalue>
  <dcvalue element="description" qualifier="abstract" language="">Volunteer&#x20;ophthalmologists&#x20;can&#x20;achieve&#x20;success&#x20;with&#x20;teaching&#x20;and&#x20;service&#x20;programs&#x20;working&#x20;with&#x20;high&#x20;intensity&#x20;over&#x20;a&#x20;short&#x20;term&#x20;Continuation&#x20;of&#x20;initially&#x20;successful&#x20;programs&#x20;may&#x20;be&#x20;limited&#x20;by&#x20;lack&#x20;of&#x20;timely&#x20;effective&#x20;communication&#x20;and&#x20;follow&#x20;up&#x20;In&#x20;an&#x20;attempt&#x20;to&#x20;overcome&#x20;these&#x20;limitations&#x20;a&#x20;total&#x20;of&#x20;6&#x20;telemedicine&#x20;programs&#x20;were&#x20;established&#x20;after&#x20;a&#x20;successful&#x20;trial&#x20;program&#x20;at&#x20;the&#x20;Ramon&#x20;Pando&#x20;Ferrer&#x20;Hospital&#x20;in&#x20;Havana&#x20;Cuba</dcvalue>
  <dcvalue element="description" qualifier="provenance" language="en">Made&#x20;available&#x20;in&#x20;DSpace&#x20;on&#x20;2020-02-12T12:01:33Z&#x20;(GMT).&#x20;No.&#x20;of&#x20;bitstreams:&#x20;0&#x0A;&#x20;&#x20;Previous&#x20;issue&#x20;date:&#x20;2001-10-19</dcvalue>
  <dcvalue element="relation" qualifier="uri" language="">Journal&#x20;of&#x20;AAPOS&#x20;:&#x20;the&#x20;official&#x20;publication&#x20;of&#x20;the&#x20;American&#x20;Association&#x20;for&#x20;Pediatric&#x20;Ophthalmology&#x20;and&#x20;Strabismus&#x20;&#x2F;&#x20;American&#x20;Association&#x20;for&#x20;Pediatric&#x20;Ophthalmology&#x20;and&#x20;Strabismus</dcvalue>
  <dcvalue element="title" qualifier="none" language="en">Telemedicine:&#x20;Strabismus&#x20;e-consultation.</dcvalue>
</dublin_core>
