<?xml version="1.0" encoding="utf-8" standalone="no"?>
<dublin_core schema="dcterms">
  <dcvalue element="contributor" qualifier="none" language="">Farrell&#x20;Carnahan,&#x20;Leah</dcvalue>
  <dcvalue element="contributor" qualifier="none" language="">Fabbri,&#x20;Stefania</dcvalue>
  <dcvalue element="contributor" qualifier="none" language="">Ingersoll,&#x20;Karen</dcvalue>
  <dcvalue element="identifier" qualifier="none" language="">http:&#x2F;&#x2F;dx.doi.org&#x2F;10.1016&#x2F;j.pec.2010.06.036</dcvalue>
  <dcvalue element="relation" qualifier="none" language="">Patient&#x20;education&#x20;and&#x20;counseling</dcvalue>
  <dcvalue element="title" qualifier="none" language="en">Technicalities:&#x20;Getting&#x20;and&#x20;staying&#x20;connected&#x20;to&#x20;people&#x20;living&#x20;with&#x20;HIV&#x2F;AIDS&#x20;in&#x20;the&#x20;southern&#x20;United&#x20;States.</dcvalue>
</dublin_core>
