<?xml version="1.0" encoding="utf-8" standalone="no"?>
<dublin_core schema="dcterms">
  <dcvalue element="abstract" qualifier="none" language="">The&#x20;2010&#x20;Academic&#x20;Emergency&#x20;Medicine&#x20;AEM&#x20;consensus&#x20;conference&#x20;Beyond&#x20;Regionalization&#x20;aimed&#x20;to&#x20;place&#x20;the&#x20;design&#x20;of&#x20;a&#x20;21st&#x20;century&#x20;emergency&#x20;care&#x20;delivery&#x20;system&#x20;at&#x20;the&#x20;center&#x20;of&#x20;emergency&#x20;medicine&#x20;s&#x20;EM&#x20;s&#x20;health&#x20;policy&#x20;research&#x20;agenda&#x20;To&#x20;examine&#x20;the&#x20;lessons&#x20;learned&#x20;from&#x20;existing&#x20;regional&#x20;systems&#x20;consensus&#x20;conference&#x20;organizers&#x20;convened&#x20;a&#x20;panel&#x20;discussion&#x20;made&#x20;up&#x20;of&#x20;experts&#x20;from&#x20;the&#x20;fields&#x20;of&#x20;acute&#x20;care&#x20;surgery&#x20;interventional&#x20;cardiology&#x20;acute&#x20;ischemic&#x20;stroke&#x20;cardiac&#x20;arrest&#x20;critical&#x20;care&#x20;medicine&#x20;pediatric&#x20;EM&#x20;and&#x20;medical&#x20;toxicology&#x20;The&#x20;organizers&#x20;asked&#x20;that&#x20;each&#x20;member&#x20;provide&#x20;insight&#x20;into&#x20;the&#x20;barriers&#x20;that&#x20;slowed&#x20;network&#x20;creation&#x20;and&#x20;the&#x20;solutions&#x20;that&#x20;allowed&#x20;them&#x20;to&#x20;overcome&#x20;barriers&#x20;For&#x20;ST&#x20;segment&#x20;elevation&#x20;myocardial&#x20;infarction&#x20;STEMI&#x20;management&#x20;the&#x20;American&#x20;Heart&#x20;Association&#x20;s&#x20;AHA&#x20;s&#x20;Mission&#x20;Lifeline&#x20;aims&#x20;to&#x20;increase&#x20;compliance&#x20;with&#x20;existing&#x20;guidelines&#x20;through&#x20;improvements&#x20;in&#x20;the&#x20;chain&#x20;of&#x20;survival&#x20;including&#x20;emergency&#x20;medical&#x20;services&#x20;EMS&#x20;protocols&#x20;Increasing&#x20;use&#x20;of&#x20;therapeutic&#x20;hypothermia&#x20;post&#x20;cardiac&#x20;arrest&#x20;through&#x20;a&#x20;network&#x20;of&#x20;hospitals&#x20;in&#x20;Virginia&#x20;has&#x20;led&#x20;to&#x20;dramatic&#x20;improvements&#x20;in&#x20;outcome&#x20;A&#x20;regionalized&#x20;network&#x20;of&#x20;acute&#x20;stroke&#x20;management&#x20;in&#x20;Cincinnati&#x20;was&#x20;discussed&#x20;in&#x20;addition&#x20;to&#x20;the&#x20;effect&#x20;of&#x20;pediatric&#x20;referral&#x20;centers&#x20;on&#x20;pediatric&#x20;capabilities&#x20;of&#x20;surrounding&#x20;facilities&#x20;The&#x20;growing&#x20;importance&#x20;of&#x20;telemedicine&#x20;to&#x20;a&#x20;variety&#x20;of&#x20;emergencies&#x20;including&#x20;trauma&#x20;and&#x20;critical&#x20;care&#x20;was&#x20;presented&#x20;Finally&#x20;the&#x20;importance&#x20;of&#x20;establishing&#x20;a&#x20;robust&#x20;reimbursement&#x20;mechanism&#x20;was&#x20;illustrated&#x20;by&#x20;the&#x20;threatened&#x20;closure&#x20;of&#x20;poison&#x20;control&#x20;centers&#x20;nationwide&#x20;The&#x20;panel&#x20;discussion&#x20;added&#x20;valuable&#x20;insight&#x20;into&#x20;the&#x20;possibilities&#x20;of&#x20;maximizing&#x20;patient&#x20;outcomes&#x20;through&#x20;regionalized&#x20;systems&#x20;of&#x20;emergency&#x20;care&#x20;A&#x20;primary&#x20;challenge&#x20;remaining&#x20;is&#x20;for&#x20;EM&#x20;to&#x20;help&#x20;to&#x20;integrate&#x20;the&#x20;existing&#x20;and&#x20;developing&#x20;disease&#x20;based&#x20;systems&#x20;of&#x20;care&#x20;into&#x20;a&#x20;more&#x20;comprehensive&#x20;emergency&#x20;care&#x20;system</dcvalue>
  <dcvalue element="contributor" qualifier="none" language="">Carr,&#x20;Brendan&#x20;G</dcvalue>
  <dcvalue element="contributor" qualifier="none" language="">Matthew&#x20;Edwards,&#x20;J</dcvalue>
  <dcvalue element="contributor" qualifier="none" language="">Martinez,&#x20;Ricardo</dcvalue>
  <dcvalue element="contributor" qualifier="none" language="">,</dcvalue>
  <dcvalue element="identifier" qualifier="none" language="">http:&#x2F;&#x2F;dx.doi.org&#x2F;10.1111&#x2F;j.1553-2712.2010.00940.x</dcvalue>
  <dcvalue element="relation" qualifier="none" language="">Academic&#x20;emergency&#x20;medicine&#x20;:&#x20;official&#x20;journal&#x20;of&#x20;the&#x20;Society&#x20;for&#x20;Academic&#x20;Emergency&#x20;Medicine</dcvalue>
  <dcvalue element="title" qualifier="none" language="en">Regionalized&#x20;care&#x20;for&#x20;time-critical&#x20;conditions:&#x20;lessons&#x20;learned&#x20;from&#x20;existing&#x20;networks.</dcvalue>
</dublin_core>
