<?xml version="1.0" encoding="utf-8" standalone="no"?>
<dublin_core schema="dcterms">
  <dcvalue element="abstract" qualifier="none" language="">Rural&#x20;populations&#x20;remain&#x20;underserved&#x20;in&#x20;terms&#x20;of&#x20;psychiatric&#x20;services&#x20;This&#x20;study&#x20;assesses&#x20;changes&#x20;over&#x20;time&#x20;in&#x20;the&#x20;utilization&#x20;of&#x20;telepsychiatric&#x20;services&#x20;by&#x20;individual&#x20;primary&#x20;care&#x20;providers&#x20;PCPs&#x20;and&#x20;clinics&#x20;in&#x20;rural&#x20;areas&#x20;specifically&#x20;a&#x20;types&#x20;of&#x20;referrals&#x20;for&#x20;telepsychiatry&#x20;service&#x20;b&#x20;PCPs&#x20;knowledge&#x20;and&#x20;skills&#x20;related&#x20;to&#x20;medication&#x20;dosing&#x20;and&#x20;c&#x20;PCPs&#x20;satisfaction&#x20;with&#x20;telepsychiatry</dcvalue>
  <dcvalue element="contributor" qualifier="none" language="">Hilty,&#x20;Donald&#x20;M</dcvalue>
  <dcvalue element="contributor" qualifier="none" language="">Yellowlees,&#x20;Peter&#x20;M</dcvalue>
  <dcvalue element="contributor" qualifier="none" language="">Nesbitt,&#x20;Thomas&#x20;S</dcvalue>
  <dcvalue element="identifier" qualifier="none" language="">http:&#x2F;&#x2F;dx.doi.org&#x2F;10.1016&#x2F;j.genhosppsych.2006.05.009</dcvalue>
  <dcvalue element="relation" qualifier="none" language="">General&#x20;hospital&#x20;psychiatry</dcvalue>
  <dcvalue element="title" qualifier="none" language="en">Evolution&#x20;of&#x20;telepsychiatry&#x20;to&#x20;rural&#x20;sites:&#x20;changes&#x20;over&#x20;time&#x20;in&#x20;types&#x20;of&#x20;referral&#x20;and&#x20;in&#x20;primary&#x20;care&#x20;providers&#39;&#x20;knowledge,&#x20;skills&#x20;and&#x20;satisfaction.</dcvalue>
</dublin_core>
