<?xml version="1.0" encoding="utf-8" standalone="no"?>
<dublin_core schema="dcterms">
  <dcvalue element="abstract" qualifier="none" language="">We&#x20;demonstrate&#x20;a&#x20;cellphone&#x20;based&#x20;contact&#x20;microscopy&#x20;platform&#x20;termed&#x20;Contact&#x20;Scope&#x20;which&#x20;can&#x20;image&#x20;highly&#x20;dense&#x20;or&#x20;connected&#x20;samples&#x20;in&#x20;transmission&#x20;mode&#x20;Weighing&#x20;approximately&#x20;76&#x20;grams&#x20;this&#x20;portable&#x20;and&#x20;compact&#x20;microscope&#x20;is&#x20;installed&#x20;on&#x20;the&#x20;existing&#x20;camera&#x20;unit&#x20;of&#x20;a&#x20;cellphone&#x20;using&#x20;an&#x20;opto&#x20;mechanical&#x20;add&#x20;on&#x20;where&#x20;planar&#x20;samples&#x20;of&#x20;interest&#x20;are&#x20;placed&#x20;in&#x20;contact&#x20;with&#x20;the&#x20;top&#x20;facet&#x20;of&#x20;a&#x20;tapered&#x20;fiber&#x20;optic&#x20;array&#x20;This&#x20;glass&#x20;based&#x20;tapered&#x20;fiber&#x20;array&#x20;has&#x20;9&#x20;fold&#x20;higher&#x20;density&#x20;of&#x20;fiber&#x20;optic&#x20;cables&#x20;on&#x20;its&#x20;top&#x20;facet&#x20;compared&#x20;to&#x20;the&#x20;bottom&#x20;one&#x20;and&#x20;is&#x20;illuminated&#x20;by&#x20;an&#x20;incoherent&#x20;light&#x20;source&#x20;e&#x20;g&#x20;a&#x20;simple&#x20;light&#x20;emitting&#x20;diode&#x20;LED&#x20;The&#x20;transmitted&#x20;light&#x20;pattern&#x20;through&#x20;the&#x20;object&#x20;is&#x20;then&#x20;sampled&#x20;by&#x20;this&#x20;array&#x20;of&#x20;fiber&#x20;optic&#x20;cables&#x20;delivering&#x20;a&#x20;transmission&#x20;image&#x20;of&#x20;the&#x20;sample&#x20;onto&#x20;the&#x20;other&#x20;side&#x20;of&#x20;the&#x20;taper&#x20;with&#x20;3&#x20;magnification&#x20;in&#x20;each&#x20;direction&#x20;This&#x20;magnified&#x20;image&#x20;of&#x20;the&#x20;object&#x20;located&#x20;at&#x20;the&#x20;bottom&#x20;facet&#x20;of&#x20;the&#x20;fiber&#x20;array&#x20;is&#x20;then&#x20;projected&#x20;onto&#x20;the&#x20;CMOS&#x20;image&#x20;sensor&#x20;of&#x20;the&#x20;cellphone&#x20;using&#x20;two&#x20;lenses&#x20;While&#x20;keeping&#x20;the&#x20;sample&#x20;and&#x20;the&#x20;cellphone&#x20;camera&#x20;at&#x20;a&#x20;fixed&#x20;position&#x20;the&#x20;fiber&#x20;optic&#x20;array&#x20;is&#x20;then&#x20;manually&#x20;rotated&#x20;with&#x20;discrete&#x20;angular&#x20;increments&#x20;of&#x20;e&#x20;g&#x20;1&#x20;2&#x20;degrees&#x20;At&#x20;each&#x20;angular&#x20;position&#x20;of&#x20;the&#x20;fiber&#x20;optic&#x20;array&#x20;contact&#x20;images&#x20;are&#x20;captured&#x20;using&#x20;the&#x20;cellphone&#x20;camera&#x20;creating&#x20;a&#x20;sequence&#x20;of&#x20;transmission&#x20;images&#x20;for&#x20;the&#x20;same&#x20;sample&#x20;These&#x20;multi&#x20;frame&#x20;images&#x20;are&#x20;digitally&#x20;fused&#x20;together&#x20;based&#x20;on&#x20;a&#x20;shift&#x20;and&#x20;add&#x20;algorithm&#x20;through&#x20;a&#x20;custom&#x20;developed&#x20;Android&#x20;application&#x20;running&#x20;on&#x20;the&#x20;smart&#x20;phone&#x20;providing&#x20;the&#x20;final&#x20;microscopic&#x20;image&#x20;of&#x20;the&#x20;sample&#x20;visualized&#x20;through&#x20;the&#x20;screen&#x20;of&#x20;the&#x20;phone&#x20;This&#x20;final&#x20;computation&#x20;step&#x20;improves&#x20;the&#x20;resolution&#x20;and&#x20;also&#x20;removes&#x20;spatial&#x20;artefacts&#x20;that&#x20;arise&#x20;due&#x20;to&#x20;non&#x20;uniform&#x20;sampling&#x20;of&#x20;the&#x20;transmission&#x20;intensity&#x20;at&#x20;the&#x20;fiber&#x20;optic&#x20;array&#x20;surface&#x20;We&#x20;validated&#x20;the&#x20;performance&#x20;of&#x20;this&#x20;cellphone&#x20;based&#x20;Contact&#x20;Scope&#x20;by&#x20;imaging&#x20;resolution&#x20;test&#x20;charts&#x20;and&#x20;blood&#x20;smears</dcvalue>
  <dcvalue element="contributor" qualifier="none" language="">Navruz,&#x20;Isa</dcvalue>
  <dcvalue element="contributor" qualifier="none" language="">Coskun,&#x20;Ahmet&#x20;F</dcvalue>
  <dcvalue element="contributor" qualifier="none" language="">Wong,&#x20;Justin</dcvalue>
  <dcvalue element="contributor" qualifier="none" language="">Mohammad,&#x20;Saqib</dcvalue>
  <dcvalue element="contributor" qualifier="none" language="">Tseng,&#x20;Derek</dcvalue>
  <dcvalue element="contributor" qualifier="none" language="">Nagi,&#x20;Richie</dcvalue>
  <dcvalue element="contributor" qualifier="none" language="">Phillips,&#x20;Stephen</dcvalue>
  <dcvalue element="contributor" qualifier="none" language="">Ozcan,&#x20;Aydogan</dcvalue>
  <dcvalue element="identifier" qualifier="none" language="">http:&#x2F;&#x2F;dx.doi.org&#x2F;10.1039&#x2F;c3lc50589h</dcvalue>
  <dcvalue element="relation" qualifier="none" language="">Lab&#x20;on&#x20;a&#x20;chip</dcvalue>
  <dcvalue element="title" qualifier="none" language="en">Smart-phone&#x20;based&#x20;computational&#x20;microscopy&#x20;using&#x20;multi-frame&#x20;contact&#x20;imaging&#x20;on&#x20;a&#x20;fiber-optic&#x20;array.</dcvalue>
</dublin_core>
