<?xml version="1.0" encoding="utf-8" standalone="no"?>
<dublin_core schema="dcterms">
  <dcvalue element="contributor" qualifier="none" language="">Fuentes,&#x20;Armando</dcvalue>
  <dcvalue element="identifier" qualifier="none" language="">http:&#x2F;&#x2F;dx.doi.org&#x2F;Not&#x20;available</dcvalue>
  <dcvalue element="relation" qualifier="none" language="">Clinical&#x20;obstetrics&#x20;and&#x20;gynecology</dcvalue>
  <dcvalue element="title" qualifier="none" language="en">Remote&#x20;interpretation&#x20;of&#x20;ultrasound&#x20;images.</dcvalue>
</dublin_core>
