<?xml version="1.0" encoding="utf-8" standalone="no"?>
<dublin_core schema="dcterms">
  <dcvalue element="abstract" qualifier="none" language="">Three&#x20;dimensional&#x20;radiotherapy&#x20;planning&#x20;is&#x20;a&#x20;complex&#x20;and&#x20;time&#x20;consuming&#x20;optimization&#x20;process&#x20;which&#x20;requires&#x20;much&#x20;experience&#x20;To&#x20;simplify&#x20;and&#x20;to&#x20;speed&#x20;up&#x20;the&#x20;process&#x20;of&#x20;treatment&#x20;planning&#x20;as&#x20;well&#x20;as&#x20;to&#x20;exchange&#x20;experience&#x20;and&#x20;therapeutic&#x20;knowledge&#x20;the&#x20;department&#x20;of&#x20;Medical&#x20;Physics&#x20;at&#x20;the&#x20;German&#x20;Cancer&#x20;Research&#x20;Centre&#x20;DKFZ&#x20;in&#x20;Heidelberg&#x20;is&#x20;developing&#x20;an&#x20;Internet&#x20;based&#x20;3D&#x20;Radiotherapy&#x20;planning&#x20;and&#x20;Information&#x20;System&#x20;IRIS&#x20;IRIS&#x20;designed&#x20;internet&#x20;based&#x20;client&#x20;server&#x20;application&#x20;implemented&#x20;using&#x20;Java&#x20;CORBA&#x20;and&#x20;PVM&#x20;The&#x20;concept&#x20;of&#x20;IRIS&#x20;combines&#x20;the&#x20;functionality&#x20;of&#x20;an&#x20;interactive&#x20;tutorial&#x20;with&#x20;a&#x20;discussion&#x20;forum&#x20;teleconferencing&#x20;tool&#x20;and&#x20;an&#x20;atlas&#x20;of&#x20;dose&#x20;distributions&#x20;Furthermore&#x20;an&#x20;integral&#x20;knowledge&#x20;based&#x20;system&#x20;provides&#x20;automatically&#x20;generated&#x20;preoptimized&#x20;treatment&#x20;plans&#x20;This&#x20;paper&#x20;explains&#x20;the&#x20;technical&#x20;design&#x20;of&#x20;the&#x20;system&#x20;and&#x20;gives&#x20;an&#x20;overview&#x20;of&#x20;experiences&#x20;gained&#x20;by&#x20;the&#x20;technical&#x20;realization&#x20;of&#x20;a&#x20;first&#x20;prototype&#x20;using&#x20;currently&#x20;available&#x20;internet&#x20;technology&#x20;The&#x20;prototype&#x20;is&#x20;currently&#x20;running&#x20;for&#x20;testing&#x20;in&#x20;the&#x20;intranet&#x20;of&#x20;DKFZ</dcvalue>
  <dcvalue element="contributor" qualifier="none" language="">Lütttgau,&#x20;A</dcvalue>
  <dcvalue element="contributor" qualifier="none" language="">Bendl,&#x20;R</dcvalue>
  <dcvalue element="identifier" qualifier="none" language="">http:&#x2F;&#x2F;dx.doi.org&#x2F;Not&#x20;available</dcvalue>
  <dcvalue element="relation" qualifier="none" language="">Medical&#x20;informatics&#x20;and&#x20;the&#x20;Internet&#x20;in&#x20;medicine</dcvalue>
  <dcvalue element="title" qualifier="none" language="en">Technical&#x20;aspects&#x20;of&#x20;internet-based&#x20;knowledge&#x20;presentation&#x20;in&#x20;radiotherapy.</dcvalue>
</dublin_core>
