<?xml version="1.0" encoding="utf-8" standalone="no"?>
<dublin_core schema="dc">
  <dcvalue element="date" qualifier="accessioned">2020-06-10T08:52:37Z</dcvalue>
  <dcvalue element="date" qualifier="available">2020-06-10T08:52:37Z</dcvalue>
  <dcvalue element="identifier" qualifier="uri">https:&#x2F;&#x2F;lib.digitalsquare.io&#x2F;handle&#x2F;123456789&#x2F;76771</dcvalue>
  <dcvalue element="description" qualifier="abstract" language="">For&#x20;LinkedIn&#x20;members&#x20;who&#x20;are&#x20;interested&#x20;in&#x20;using&#x20;mobiles&#x20;to&#x20;improve&#x20;health</dcvalue>
  <dcvalue element="description" qualifier="provenance" language="en">Made&#x20;available&#x20;in&#x20;DSpace&#x20;on&#x20;2020-06-10T08:52:37Z&#x20;(GMT).&#x20;No.&#x20;of&#x20;bitstreams:&#x20;2&#x0A;http-www.linkedin.com-groups-mHealth-1049717-about.pdf:&#x20;4678&#x20;bytes,&#x20;checksum:&#x20;73a68e6e480cda2d8a077ab0998f67ec&#x20;(MD5)&#x0A;http-www.linkedin.com-groups-mHealth-1049717-about:&#x20;159619&#x20;bytes,&#x20;checksum:&#x20;f74bd290c0bfdc35a1941e749fd2040d&#x20;(MD5)</dcvalue>
  <dcvalue element="subject" qualifier="none" language="">Communities&#x20;of&#x20;Practice</dcvalue>
  <dcvalue element="title" qualifier="none" language="en">mHealth&#x20;Group</dcvalue>
  <dcvalue element="title" qualifier="alternative" language="">mHealth&#x20;Group</dcvalue>
</dublin_core>
