<?xml version="1.0" encoding="utf-8" standalone="no"?>
<dublin_core schema="dcterms">
  <dcvalue element="abstract" qualifier="none" language="">Can&#x20;informatics&#x20;improve&#x20;health&#x20;This&#x20;paper&#x20;answers&#x20;yes&#x20;exploring&#x20;its&#x20;components&#x20;benefits&#x20;and&#x20;effect&#x20;on&#x20;a&#x20;wide&#x20;variety&#x20;of&#x20;health&#x20;related&#x20;activities&#x20;We&#x20;first&#x20;examine&#x20;how&#x20;information&#x20;technology&#x20;enables&#x20;health&#x20;informatics&#x20;supporting&#x20;information&#x20;management&#x20;and&#x20;knowledge&#x20;creation&#x20;through&#x20;its&#x20;four&#x20;cornerstones&#x20;Success&#x20;factors&#x20;in&#x20;using&#x20;informatics&#x20;are&#x20;covered&#x20;next&#x20;including&#x20;human&#x20;factors&#x20;the&#x20;role&#x20;of&#x20;trained&#x20;health&#x20;informaticians&#x20;and&#x20;the&#x20;importance&#x20;of&#x20;matching&#x20;informatics&#x20;initiatives&#x20;with&#x20;business&#x20;goals&#x20;and&#x20;establishing&#x20;and&#x20;measuring&#x20;value&#x20;We&#x20;demonstrate&#x20;the&#x20;potential&#x20;effect&#x20;of&#x20;the&#x20;Internet&#x20;on&#x20;health&#x20;services&#x20;through&#x20;such&#x20;e&#x20;health&#x20;applications&#x20;as&#x20;enterprise&#x20;wide&#x20;patient&#x20;records&#x20;state&#x20;of&#x20;the&#x20;art&#x20;call&#x20;centers&#x20;and&#x20;data&#x20;repositories&#x20;For&#x20;current&#x20;evidence&#x20;that&#x20;informatics&#x20;is&#x20;already&#x20;improving&#x20;health&#x20;we&#x20;turn&#x20;to&#x20;such&#x20;topics&#x20;as&#x20;disease&#x20;management&#x20;telehealth&#x20;patient&#x20;safety&#x20;and&#x20;decision&#x20;support&#x20;As&#x20;more&#x20;organizations&#x20;move&#x20;informatics&#x20;from&#x20;theory&#x20;into&#x20;practice&#x20;and&#x20;realize&#x20;its&#x20;value&#x20;they&#x20;will&#x20;transform&#x20;inefficient&#x20;processes&#x20;and&#x20;improve&#x20;care&#x20;for&#x20;all</dcvalue>
  <dcvalue element="contributor" qualifier="none" language="">Ball,&#x20;M&#x20;J</dcvalue>
  <dcvalue element="contributor" qualifier="none" language="">Douglas,&#x20;J&#x20;V</dcvalue>
  <dcvalue element="contributor" qualifier="none" language="">Lillis,&#x20;J</dcvalue>
  <dcvalue element="identifier" qualifier="none" language="">http:&#x2F;&#x2F;dx.doi.org&#x2F;Not&#x20;available</dcvalue>
  <dcvalue element="relation" qualifier="none" language="">Studies&#x20;in&#x20;health&#x20;technology&#x20;and&#x20;informatics</dcvalue>
  <dcvalue element="title" qualifier="none" language="en">Health&#x20;informatics:&#x20;managing&#x20;information&#x20;to&#x20;deliver&#x20;value.</dcvalue>
</dublin_core>
