<?xml version="1.0" encoding="utf-8" standalone="no"?>
<dublin_core schema="dcterms">
  <dcvalue element="abstract" qualifier="none" language="">BACKGROUND&#x20;Many&#x20;patients&#x20;experience&#x20;difficulties&#x20;in&#x20;adhering&#x20;to&#x20;long&#x20;term&#x20;treatment&#x20;Although&#x20;patients&#x20;reasons&#x20;for&#x20;not&#x20;being&#x20;adherent&#x20;are&#x20;diverse&#x20;one&#x20;of&#x20;the&#x20;most&#x20;commonly&#x20;reported&#x20;barriers&#x20;is&#x20;forgetfulness&#x20;Reminding&#x20;patients&#x20;to&#x20;take&#x20;their&#x20;medication&#x20;may&#x20;provide&#x20;a&#x20;solution&#x20;Electronic&#x20;reminders&#x20;automatically&#x20;sent&#x20;reminders&#x20;without&#x20;personal&#x20;contact&#x20;between&#x20;the&#x20;healthcare&#x20;provider&#x20;and&#x20;patient&#x20;are&#x20;now&#x20;increasingly&#x20;being&#x20;used&#x20;in&#x20;the&#x20;effort&#x20;to&#x20;improve&#x20;adherence&#x20;OBJECTIVE&#x20;To&#x20;examine&#x20;the&#x20;effectiveness&#x20;of&#x20;interventions&#x20;using&#x20;electronic&#x20;reminders&#x20;in&#x20;improving&#x20;patients&#x20;adherence&#x20;to&#x20;chronic&#x20;medication&#x20;METHODS&#x20;A&#x20;comprehensive&#x20;literature&#x20;search&#x20;was&#x20;conducted&#x20;in&#x20;PubMed&#x20;Embase&#x20;PsycINFO&#x20;CINAHL&#x20;and&#x20;Cochrane&#x20;Central&#x20;Register&#x20;of&#x20;Controlled&#x20;Trials&#x20;Electronic&#x20;searches&#x20;were&#x20;supplemented&#x20;by&#x20;manual&#x20;searching&#x20;of&#x20;reference&#x20;lists&#x20;and&#x20;reviews&#x20;Two&#x20;reviewers&#x20;independently&#x20;screened&#x20;all&#x20;citations&#x20;Full&#x20;text&#x20;was&#x20;obtained&#x20;from&#x20;selected&#x20;citations&#x20;and&#x20;screened&#x20;for&#x20;final&#x20;inclusion&#x20;The&#x20;methodological&#x20;quality&#x20;of&#x20;studies&#x20;was&#x20;assessed&#x20;RESULTS&#x20;Thirteen&#x20;studies&#x20;met&#x20;the&#x20;inclusion&#x20;criteria&#x20;Four&#x20;studies&#x20;evaluated&#x20;short&#x20;message&#x20;service&#x20;SMS&#x20;reminders&#x20;seven&#x20;audiovisual&#x20;reminders&#x20;from&#x20;electronic&#x20;reminder&#x20;devices&#x20;ERD&#x20;and&#x20;two&#x20;pager&#x20;messages&#x20;Best&#x20;evidence&#x20;synthesis&#x20;revealed&#x20;evidence&#x20;for&#x20;the&#x20;effectiveness&#x20;of&#x20;electronic&#x20;reminders&#x20;provided&#x20;by&#x20;eight&#x20;four&#x20;high&#x20;four&#x20;low&#x20;quality&#x20;studies&#x20;showing&#x20;significant&#x20;effects&#x20;on&#x20;patients&#x20;adherence&#x20;seven&#x20;of&#x20;which&#x20;measured&#x20;short&#x20;term&#x20;effects&#x20;follow&#x20;up&#x20;period&#x20;Under6&#x20;months&#x20;Improved&#x20;adherence&#x20;was&#x20;found&#x20;in&#x20;all&#x20;but&#x20;one&#x20;study&#x20;using&#x20;SMS&#x20;reminders&#x20;four&#x20;studies&#x20;using&#x20;ERD&#x20;and&#x20;one&#x20;pager&#x20;intervention&#x20;In&#x20;addition&#x20;one&#x20;high&#x20;quality&#x20;study&#x20;using&#x20;an&#x20;ERD&#x20;found&#x20;subgroup&#x20;effects&#x20;CONCLUSION&#x20;This&#x20;review&#x20;provides&#x20;evidence&#x20;for&#x20;the&#x20;short&#x20;term&#x20;effectiveness&#x20;of&#x20;electronic&#x20;reminders&#x20;especially&#x20;SMS&#x20;reminders&#x20;However&#x20;long&#x20;term&#x20;effects&#x20;remain&#x20;unclear</dcvalue>
  <dcvalue element="contributor" qualifier="none" language="">Vervloet,&#x20;Marcia</dcvalue>
  <dcvalue element="contributor" qualifier="none" language="">Linn,&#x20;Annemiek&#x20;J</dcvalue>
  <dcvalue element="contributor" qualifier="none" language="">van&#x20;Weert,&#x20;Julia&#x20;C&#x20;M</dcvalue>
  <dcvalue element="contributor" qualifier="none" language="">de&#x20;Bakker,&#x20;Dinny&#x20;H</dcvalue>
  <dcvalue element="contributor" qualifier="none" language="">Bouvy,&#x20;Marcel&#x20;L</dcvalue>
  <dcvalue element="contributor" qualifier="none" language="">van&#x20;Dijk,&#x20;Liset</dcvalue>
  <dcvalue element="identifier" qualifier="none" language="">http:&#x2F;&#x2F;dx.doi.org&#x2F;10.1136&#x2F;amiajnl-2011-000748</dcvalue>
  <dcvalue element="relation" qualifier="none" language="">Journal&#x20;of&#x20;the&#x20;American&#x20;Medical&#x20;Informatics&#x20;Association&#x20;:&#x20;JAMIA</dcvalue>
  <dcvalue element="title" qualifier="none" language="en">The&#x20;effectiveness&#x20;of&#x20;interventions&#x20;using&#x20;electronic&#x20;reminders&#x20;to&#x20;improve&#x20;adherence&#x20;to&#x20;chronic&#x20;medication:&#x20;a&#x20;systematic&#x20;review&#x20;of&#x20;the&#x20;literature.</dcvalue>
</dublin_core>
