<?xml version="1.0" encoding="utf-8" standalone="no"?>
<dublin_core schema="dc">
  <dcvalue element="contributor" qualifier="other" language="">Sara&#x20;Chamberlain,&#x20;Director,&#x20;Digital,&#x20;BBC&#x20;Media&#x20;Action&#x20;sara.chamberlain@in.bbcmediaaction.org&#x20;&#x0A;Malika&#x20;Malhotra,&#x20;Project&#x20;Director,&#x20;National&#x20;Scale-up,&#x20;BBC&#x20;Media&#x20;Action&#x20;malika.malhotra@in.bbcmediaaction.org</dcvalue>
  <dcvalue element="coverage" qualifier="spatial" language="">Mobile&#x20;Kunji&#x20;-&#x20;Bihar,&#x20;Odisha,&#x20;Uttar&#x20;Pradesh&#x20;&#x0A;Mobile&#x20;Academy&#x20;-&#x20;Bihar,&#x20;Odisha,&#x20;Uttar&#x20;Pradesh,&#x20;Rajasthan,&#x20;Madhya&#x20;Pradesh,&#x20;Jharkhand&#x20;and&#x20;Uttarakhand&#x0A;Kilkari&#x20;-&#x20;Bihar,&#x20;Uttar&#x20;Pradesh,&#x20;Rajasthan,&#x20;Madhya&#x20;Pradesh,&#x20;Jharkhand&#x20;and&#x20;Uttarakhand</dcvalue>
  <dcvalue element="date" qualifier="accessioned">2020-10-14T10:19:27Z</dcvalue>
  <dcvalue element="date" qualifier="available">2020-10-14T10:19:27Z</dcvalue>
  <dcvalue element="identifier" qualifier="uri">https:&#x2F;&#x2F;lib.digitalsquare.io&#x2F;handle&#x2F;123456789&#x2F;77606</dcvalue>
  <dcvalue element="description" qualifier="abstract" language="">Mobile&#x20;Kunji,&#x20;Mobile&#x20;Academy,&#x20;and&#x20;Kilkari&#x20;all&#x20;use&#x20;IVR&#x20;technology&#x20;that&#x20;is&#x20;already&#x20;being&#x20;used&#x20;by&#x20;the&#x20;commercial&#x20;mobile&#x20;industry&#x20;to&#x20;make&#x20;audio&#x20;content&#x20;available&#x20;to&#x20;any&#x20;mobile&#x20;phone&#x20;across&#x20;India.&#x20;At&#x20;the&#x20;national&#x20;level,&#x20;both&#x20;Mobile&#x20;Academy&#x20;and&#x20;Kilkari&#x20;have&#x20;been&#x20;integrated&#x20;with&#x20;the&#x20;government’s&#x20;Maternal&#x20;and&#x20;Child&#x20;Tracking&#x20;System&#x20;(MCTS).</dcvalue>
  <dcvalue element="description" qualifier="provenance" language="en">Made&#x20;available&#x20;in&#x20;DSpace&#x20;on&#x20;2020-10-14T10:19:27Z&#x20;(GMT).&#x20;No.&#x20;of&#x20;bitstreams:&#x20;1&#x0A;mobile_kunji_mobile_academy_kilkari_se.pdf:&#x20;477605&#x20;bytes,&#x20;checksum:&#x20;33e6974799e787678c8d02a898472e75&#x20;(MD5)</dcvalue>
  <dcvalue element="description" qualifier="sponsorship" language="">Bill&#x20;&amp;&#x20;Melinda&#x20;Gates&#x20;Foundation,&#x20;USAID</dcvalue>
  <dcvalue element="subject" qualifier="none" language="">Behavior&#x20;Change&#x20;Communication</dcvalue>
  <dcvalue element="title" qualifier="none" language="en">Mobile&#x20;Kunji,&#x20;Mobile&#x20;Academy,&#x20;Kilkari</dcvalue>
  <dcvalue element="title" qualifier="alternative" language="">Mobile&#x20;Kunji,&#x20;Mobile&#x20;Academy,&#x20;Kilkari</dcvalue>
  <dcvalue element="type" qualifier="none" language="">Client&#x20;education&#x20;and&#x20;behavior&#x20;change&#x20;communication,&#x20;Child&#x20;health,&#x20;Family&#x20;Planning,&#x20;Maternal&#x20;health,&#x20;Newborn&#x20;heath,&#x20;Nutrition&#x2F;Food&#x20;Security,&#x20;Sexual&#x20;and&#x20;Reproductive&#x20;Health,&#x20;Water,&#x20;Sanitation,&#x20;and&#x20;Hygiene</dcvalue>
</dublin_core>
