<?xml version="1.0" encoding="utf-8" standalone="no"?>
<dublin_core schema="dcterms">
  <dcvalue element="abstract" qualifier="none" language="">Consumers&#x20;use&#x20;pharmaceutical&#x20;database&#x20;to&#x20;match&#x20;single-use&#x20;codes&#x20;on&#x20;packaging&#x20;to&#x20;verify&#x20;origin&#x20;and&#x20;authenticity&#x20;of&#x20;drug&#x20;treatments&#x20;before&#x20;use</dcvalue>
  <dcvalue element="alternative" qualifier="none" language="">mPedigree</dcvalue>
  <dcvalue element="audience" qualifier="none" language="">Patient&#x20;or&#x20;community&#x20;member,&#x20;None</dcvalue>
  <dcvalue element="contributor" qualifier="none" language="">Bright&#x20;Simons,&#x20;President,&#x20;mPedigree&#x20;Network&#x20;|&#x20;Email:&#x20;info@mpedigree.net</dcvalue>
  <dcvalue element="coverage" qualifier="none" language="">Ghana,&#x20;India,&#x20;East&#x20;Africa,&#x20;Nigeria&#x20;and&#x20;South&#x20;Africa</dcvalue>
  <dcvalue element="description" qualifier="none" language="">The&#x20;US&#x20;Technical&#x20;Support&#x20;Working&#x20;Group</dcvalue>
  <dcvalue element="subject" qualifier="none" language="">Logistics</dcvalue>
  <dcvalue element="title" qualifier="none" language="">mPedigree</dcvalue>
  <dcvalue element="type" qualifier="none" language="">Supply&#x20;chain&#x20;management,&#x20;Child&#x20;health,&#x20;Family&#x20;planning,&#x20;HIV&#x2F;AIDS,&#x20;Infectious&#x20;diseases,&#x20;Malaria&#x20;and&#x20;other&#x20;vector-borne&#x20;diseases,&#x20;Maternal&#x20;health,&#x20;Newborn&#x20;health,&#x20;Non-communicable&#x20;diseases,&#x20;Nutrition,&#x20;Parasitic&#x20;diseases,&#x20;Primary&#x20;Care,&#x20;Sexual&#x20;and&#x20;reproductive&#x20;health,&#x20;Tuberculosis,&#x20;Domestic&#x20;violence,&#x20;Water,&#x20;sanitation,&#x20;and&#x20;hygiene</dcvalue>
</dublin_core>
