<?xml version="1.0" encoding="utf-8" standalone="no"?>
<dublin_core schema="dcterms">
  <dcvalue element="contributor" qualifier="none" language="">Back,&#x20;Mitja&#x20;D</dcvalue>
  <dcvalue element="contributor" qualifier="none" language="">Küfner,&#x20;Albrecht&#x20;C&#x20;P</dcvalue>
  <dcvalue element="contributor" qualifier="none" language="">Egloff,&#x20;Boris</dcvalue>
  <dcvalue element="identifier" qualifier="none" language="">http:&#x2F;&#x2F;dx.doi.org&#x2F;10.1177&#x2F;0956797610382124</dcvalue>
  <dcvalue element="relation" qualifier="none" language="">Psychological&#x20;science</dcvalue>
  <dcvalue element="title" qualifier="none" language="en">The&#x20;emotional&#x20;timeline&#x20;of&#x20;September&#x20;11,&#x20;2001.</dcvalue>
</dublin_core>
