<?xml version="1.0" encoding="utf-8" standalone="no"?>
<dublin_core schema="dcterms">
  <dcvalue element="contributor" qualifier="none" language="">Baffoni,&#x20;L</dcvalue>
  <dcvalue element="contributor" qualifier="none" language="">Barone,&#x20;D</dcvalue>
  <dcvalue element="contributor" qualifier="none" language="">Benea,&#x20;G</dcvalue>
  <dcvalue element="contributor" qualifier="none" language="">Borasi,&#x20;G</dcvalue>
  <dcvalue element="contributor" qualifier="none" language="">Capotondi,&#x20;C</dcvalue>
  <dcvalue element="contributor" qualifier="none" language="">Caramella,&#x20;D</dcvalue>
  <dcvalue element="contributor" qualifier="none" language="">Giovagnoni,&#x20;A</dcvalue>
  <dcvalue element="contributor" qualifier="none" language="">Golfieri,&#x20;R</dcvalue>
  <dcvalue element="contributor" qualifier="none" language="">Laghi,&#x20;A</dcvalue>
  <dcvalue element="contributor" qualifier="none" language="">Maggi,&#x20;S</dcvalue>
  <dcvalue element="contributor" qualifier="none" language="">Moser,&#x20;E</dcvalue>
  <dcvalue element="contributor" qualifier="none" language="">Neri,&#x20;E</dcvalue>
  <dcvalue element="contributor" qualifier="none" language="">Nitrosi,&#x20;A</dcvalue>
  <dcvalue element="contributor" qualifier="none" language="">Padovani,&#x20;L</dcvalue>
  <dcvalue element="contributor" qualifier="none" language="">Panebianco,&#x20;V</dcvalue>
  <dcvalue element="contributor" qualifier="none" language="">Pedroli,&#x20;G</dcvalue>
  <dcvalue element="contributor" qualifier="none" language="">Ramelli,&#x20;A</dcvalue>
  <dcvalue element="contributor" qualifier="none" language="">Rollandi,&#x20;G&#x20;A</dcvalue>
  <dcvalue element="contributor" qualifier="none" language="">Saccavini,&#x20;C</dcvalue>
  <dcvalue element="contributor" qualifier="none" language="">Sacco,&#x20;P</dcvalue>
  <dcvalue element="contributor" qualifier="none" language="">Silverio,&#x20;R</dcvalue>
  <dcvalue element="contributor" qualifier="none" language="">Tamburrini,&#x20;O</dcvalue>
  <dcvalue element="contributor" qualifier="none" language="">Torresin,&#x20;A</dcvalue>
  <dcvalue element="contributor" qualifier="none" language="">Vanzulli,&#x20;A</dcvalue>
  <dcvalue element="contributor" qualifier="none" language="">,</dcvalue>
  <dcvalue element="identifier" qualifier="none" language="">http:&#x2F;&#x2F;dx.doi.org&#x2F;Not&#x20;available</dcvalue>
  <dcvalue element="relation" qualifier="none" language="">La&#x20;Radiologia&#x20;medica</dcvalue>
  <dcvalue element="title" qualifier="none" language="en">[PACS&#x20;(Picture&#x20;Archiving&#x20;and&#x20;Communication&#x20;Systems).&#x20;General&#x20;principles&#x20;and&#x20;guidelines&#x20;for&#x20;its&#x20;use].</dcvalue>
</dublin_core>
