<?xml version="1.0" encoding="utf-8" standalone="no"?>
<dublin_core schema="dcterms">
  <dcvalue element="abstract" qualifier="none" language="">We&#x20;describe&#x20;a&#x20;system&#x20;which&#x20;provides&#x20;high&#x20;fidelity&#x20;haptic&#x20;feedback&#x20;in&#x20;the&#x20;same&#x20;physical&#x20;location&#x20;as&#x20;a&#x20;3D&#x20;graphical&#x20;display&#x20;in&#x20;order&#x20;to&#x20;enable&#x20;realistic&#x20;physical&#x20;interaction&#x20;with&#x20;virtual&#x20;anatomical&#x20;tissue&#x20;during&#x20;modelled&#x20;procedures&#x20;such&#x20;as&#x20;needle&#x20;driving&#x20;palpation&#x20;and&#x20;other&#x20;interventions&#x20;performed&#x20;using&#x20;handheld&#x20;instruments&#x20;The&#x20;haptic&#x20;feedback&#x20;is&#x20;produced&#x20;by&#x20;the&#x20;interaction&#x20;between&#x20;an&#x20;array&#x20;of&#x20;coils&#x20;located&#x20;behind&#x20;a&#x20;thin&#x20;flat&#x20;LCD&#x20;screen&#x20;and&#x20;permanent&#x20;magnets&#x20;embedded&#x20;in&#x20;the&#x20;instrument&#x20;held&#x20;by&#x20;the&#x20;user&#x20;The&#x20;coil&#x20;and&#x20;magnet&#x20;configuration&#x20;permits&#x20;arbitrary&#x20;forces&#x20;and&#x20;torques&#x20;to&#x20;be&#x20;generated&#x20;on&#x20;the&#x20;instrument&#x20;in&#x20;real&#x20;time&#x20;according&#x20;to&#x20;the&#x20;dynamics&#x20;of&#x20;the&#x20;simulated&#x20;tissue&#x20;by&#x20;activating&#x20;the&#x20;coils&#x20;in&#x20;combination&#x20;A&#x20;rigid&#x20;body&#x20;motion&#x20;tracker&#x20;provides&#x20;position&#x20;and&#x20;orientation&#x20;feedback&#x20;of&#x20;the&#x20;handheld&#x20;instrument&#x20;to&#x20;the&#x20;computer&#x20;simulation&#x20;and&#x20;the&#x20;3D&#x20;display&#x20;is&#x20;produced&#x20;using&#x20;LCD&#x20;shutter&#x20;glasses&#x20;and&#x20;a&#x20;head&#x20;tracking&#x20;system&#x20;for&#x20;the&#x20;user</dcvalue>
  <dcvalue element="contributor" qualifier="none" language="">Berkelman,&#x20;Peter</dcvalue>
  <dcvalue element="contributor" qualifier="none" language="">Miyasaka,&#x20;Muneaki</dcvalue>
  <dcvalue element="contributor" qualifier="none" language="">Bozlee,&#x20;Sebastian</dcvalue>
  <dcvalue element="identifier" qualifier="none" language="">http:&#x2F;&#x2F;dx.doi.org&#x2F;Not&#x20;available</dcvalue>
  <dcvalue element="relation" qualifier="none" language="">Studies&#x20;in&#x20;health&#x20;technology&#x20;and&#x20;informatics</dcvalue>
  <dcvalue element="title" qualifier="none" language="en">Co-located&#x20;haptic&#x20;and&#x20;3D&#x20;graphic&#x20;interface&#x20;for&#x20;medical&#x20;simulations.</dcvalue>
</dublin_core>
