<?xml version="1.0" encoding="utf-8" standalone="no"?>
<dublin_core schema="dc">
  <dcvalue element="contributor" qualifier="author" language="">Kaufman,&#x20;David&#x20;R</dcvalue>
  <dcvalue element="contributor" qualifier="author" language="">Patel,&#x20;Vimla&#x20;L</dcvalue>
  <dcvalue element="contributor" qualifier="author" language="">Hilliman,&#x20;Charlyn</dcvalue>
  <dcvalue element="contributor" qualifier="author" language="">Morin,&#x20;Philip&#x20;C</dcvalue>
  <dcvalue element="contributor" qualifier="author" language="">Pevzner,&#x20;Jenia</dcvalue>
  <dcvalue element="contributor" qualifier="author" language="">Weinstock,&#x20;Ruth&#x20;S</dcvalue>
  <dcvalue element="contributor" qualifier="author" language="">Goland,&#x20;Robin</dcvalue>
  <dcvalue element="contributor" qualifier="author" language="">Shea,&#x20;Steven</dcvalue>
  <dcvalue element="contributor" qualifier="author" language="">Starren,&#x20;Justin</dcvalue>
  <dcvalue element="date" qualifier="accessioned">2020-02-12T11:39:52Z</dcvalue>
  <dcvalue element="date" qualifier="available">2020-02-12T11:39:52Z</dcvalue>
  <dcvalue element="date" qualifier="issued" language="">2003-10-13</dcvalue>
  <dcvalue element="identifier" qualifier="uri" language="">http:&#x2F;&#x2F;dx.doi.org&#x2F;Not&#x20;available</dcvalue>
  <dcvalue element="identifier" qualifier="uri">https:&#x2F;&#x2F;lib.digitalsquare.io&#x2F;xmlui&#x2F;handle&#x2F;123456789&#x2F;57850</dcvalue>
  <dcvalue element="description" qualifier="abstract" language="">This&#x20;paper&#x20;presents&#x20;an&#x20;approach&#x20;to&#x20;usability&#x20;evaluation&#x20;of&#x20;computer&#x20;based&#x20;health&#x20;care&#x20;systems&#x20;designed&#x20;for&#x20;patient&#x20;use&#x20;in&#x20;their&#x20;homes&#x20;Although&#x20;such&#x20;devices&#x20;are&#x20;becoming&#x20;more&#x20;prevalent&#x20;there&#x20;is&#x20;very&#x20;little&#x20;known&#x20;about&#x20;their&#x20;usability</dcvalue>
  <dcvalue element="description" qualifier="provenance" language="en">Made&#x20;available&#x20;in&#x20;DSpace&#x20;on&#x20;2020-02-12T11:39:52Z&#x20;(GMT).&#x20;No.&#x20;of&#x20;bitstreams:&#x20;0&#x0A;&#x20;&#x20;Previous&#x20;issue&#x20;date:&#x20;2003-10-13</dcvalue>
  <dcvalue element="relation" qualifier="uri" language="">Journal&#x20;of&#x20;biomedical&#x20;informatics</dcvalue>
  <dcvalue element="title" qualifier="none" language="en">Usability&#x20;in&#x20;the&#x20;real&#x20;world:&#x20;assessing&#x20;medical&#x20;information&#x20;technologies&#x20;in&#x20;patients&#39;&#x20;homes.</dcvalue>
</dublin_core>
