<?xml version="1.0" encoding="utf-8" standalone="no"?>
<dublin_core schema="dcterms">
  <dcvalue element="abstract" qualifier="none" language="">This&#x20;new&#x20;section&#x20;in&#x20;Critical&#x20;Care&#x20;presents&#x20;a&#x20;selection&#x20;of&#x20;clinically&#x20;important&#x20;examples&#x20;of&#x20;advances&#x20;in&#x20;critical&#x20;care&#x20;health&#x20;technology&#x20;This&#x20;article&#x20;is&#x20;divided&#x20;into&#x20;two&#x20;main&#x20;areas&#x20;diagnostics&#x20;and&#x20;monitoring&#x20;Attention&#x20;is&#x20;given&#x20;to&#x20;how&#x20;bedside&#x20;echocardiography&#x20;can&#x20;alter&#x20;the&#x20;cardiovascular&#x20;physical&#x20;examination&#x20;and&#x20;to&#x20;novel&#x20;imaging&#x20;techniques&#x20;such&#x20;as&#x20;virtual&#x20;bronchoscopy&#x20;The&#x20;monitoring&#x20;section&#x20;discusses&#x20;recent&#x20;claims&#x20;of&#x20;improved&#x20;efficiency&#x20;with&#x20;telemedicine&#x20;for&#x20;intensive&#x20;care&#x20;units</dcvalue>
  <dcvalue element="contributor" qualifier="none" language="">Chapman,&#x20;Martin</dcvalue>
  <dcvalue element="contributor" qualifier="none" language="">Gattas,&#x20;David</dcvalue>
  <dcvalue element="contributor" qualifier="none" language="">Suntharalingam,&#x20;Ganesh</dcvalue>
  <dcvalue element="identifier" qualifier="none" language="">http:&#x2F;&#x2F;dx.doi.org&#x2F;10.1186&#x2F;cc2843</dcvalue>
  <dcvalue element="relation" qualifier="none" language="">Critical&#x20;care&#x20;(London,&#x20;England)</dcvalue>
  <dcvalue element="title" qualifier="none" language="en">Innovations&#x20;in&#x20;technology&#x20;for&#x20;critical&#x20;care&#x20;medicine.</dcvalue>
</dublin_core>
