<?xml version="1.0" encoding="utf-8" standalone="no"?>
<dublin_core schema="dcterms">
  <dcvalue element="abstract" qualifier="none" language="">Portable&#x20;media&#x20;consoles&#x20;are&#x20;becoming&#x20;extremely&#x20;popular&#x20;devices&#x20;for&#x20;viewing&#x20;a&#x20;number&#x20;of&#x20;different&#x20;types&#x20;of&#x20;media&#x20;content&#x20;both&#x20;for&#x20;entertainment&#x20;and&#x20;for&#x20;educational&#x20;purposes&#x20;Given&#x20;the&#x20;increasingly&#x20;heavy&#x20;use&#x20;of&#x20;portable&#x20;consoles&#x20;as&#x20;an&#x20;alternative&#x20;to&#x20;traditional&#x20;television&#x20;style&#x20;monitors&#x20;it&#x20;is&#x20;important&#x20;to&#x20;investigate&#x20;how&#x20;physiological&#x20;and&#x20;psychological&#x20;effects&#x20;of&#x20;portable&#x20;consoles&#x20;may&#x20;differ&#x20;from&#x20;those&#x20;of&#x20;television&#x20;based&#x20;consoles&#x20;because&#x20;such&#x20;differences&#x20;in&#x20;physiological&#x20;and&#x20;psychological&#x20;responses&#x20;may&#x20;precipitate&#x20;differences&#x20;in&#x20;the&#x20;delivered&#x20;content&#x20;s&#x20;effectiveness&#x20;Because&#x20;portable&#x20;consoles&#x20;are&#x20;popular&#x20;as&#x20;a&#x20;delivery&#x20;system&#x20;for&#x20;multiple&#x20;types&#x20;of&#x20;media&#x20;content&#x20;such&#x20;as&#x20;movies&#x20;and&#x20;video&#x20;games&#x20;it&#x20;is&#x20;also&#x20;important&#x20;to&#x20;investigate&#x20;whether&#x20;differences&#x20;between&#x20;the&#x20;effects&#x20;of&#x20;portable&#x20;and&#x20;television&#x20;based&#x20;consoles&#x20;are&#x20;consistent&#x20;across&#x20;multiple&#x20;types&#x20;of&#x20;media&#x20;This&#x20;article&#x20;reports&#x20;a&#x20;2&#x20;x&#x20;2&#x20;console&#x20;portable&#x20;or&#x20;television&#x20;based&#x20;x&#x20;medium&#x20;video&#x20;game&#x20;or&#x20;movie&#x20;mixed&#x20;factorial&#x20;design&#x20;experiment&#x20;with&#x20;physiological&#x20;arousal&#x20;and&#x20;self&#x20;reported&#x20;flow&#x20;experience&#x20;as&#x20;dependent&#x20;variables&#x20;designed&#x20;to&#x20;explore&#x20;whether&#x20;console&#x20;type&#x20;affects&#x20;media&#x20;experiences&#x20;and&#x20;whether&#x20;these&#x20;effects&#x20;are&#x20;consistent&#x20;across&#x20;different&#x20;media&#x20;Results&#x20;indicate&#x20;that&#x20;portable&#x20;media&#x20;consoles&#x20;evoke&#x20;lower&#x20;levels&#x20;of&#x20;physiological&#x20;arousal&#x20;and&#x20;flow&#x20;experience&#x20;and&#x20;that&#x20;this&#x20;effect&#x20;is&#x20;consistent&#x20;for&#x20;both&#x20;video&#x20;games&#x20;and&#x20;movies&#x20;These&#x20;findings&#x20;suggest&#x20;that&#x20;even&#x20;though&#x20;portable&#x20;media&#x20;consoles&#x20;are&#x20;often&#x20;convenient&#x20;compared&#x20;to&#x20;television&#x20;based&#x20;consoles&#x20;the&#x20;convenience&#x20;may&#x20;come&#x20;at&#x20;a&#x20;cost&#x20;in&#x20;terms&#x20;of&#x20;the&#x20;user&#x20;experience</dcvalue>
  <dcvalue element="contributor" qualifier="none" language="">Ivory,&#x20;James&#x20;D</dcvalue>
  <dcvalue element="contributor" qualifier="none" language="">Magee,&#x20;Robert&#x20;G</dcvalue>
  <dcvalue element="identifier" qualifier="none" language="">http:&#x2F;&#x2F;dx.doi.org&#x2F;10.1089&#x2F;cpb.2008.0279</dcvalue>
  <dcvalue element="relation" qualifier="none" language="">Cyberpsychology&#x20;And&#x20;behavior&#x20;:&#x20;the&#x20;impact&#x20;of&#x20;the&#x20;Internet,&#x20;multimedia&#x20;and&#x20;virtual&#x20;reality&#x20;on&#x20;behavior&#x20;and&#x20;society</dcvalue>
  <dcvalue element="title" qualifier="none" language="en">You&#x20;can&#39;t&#x20;take&#x20;it&#x20;with&#x20;you?&#x20;Effects&#x20;of&#x20;handheld&#x20;portable&#x20;media&#x20;consoles&#x20;on&#x20;physiological&#x20;and&#x20;psychological&#x20;responses&#x20;to&#x20;video&#x20;game&#x20;and&#x20;movie&#x20;content.</dcvalue>
</dublin_core>
